{
  "borderRadius": "0px",
  "bottomRow": 4,
  "boxShadow": "none",
  "disableLink": false,
  "dynamicBindingPathList": [
    {
      "key": "text"
    }
  ],
  "dynamicHeight": "AUTO_HEIGHT",
  "dynamicTriggerPathList": [],
  "fontFamily": "System Default",
  "fontSize": "1rem",
  "fontStyle": "BOLD",
  "isLoading": false,
  "isVisible": true,
  "labelTextSize": "0.875rem",
  "leftColumn": 23.17241379310345,
  "maxDynamicHeight": 9000,
  "minDynamicHeight": 4,
  "originalBottomRow": 4,
  "originalTopRow": 0,
  "overflow": "NONE",
  "parentColumnSpace": 7.054412841796875,
  "parentId": "isryr08mla",
  "parentRowSpace": 10,
  "rightColumn": 62.89655172413793,
  "shouldScrollContents": true,
  "text": "{{data_table.selectedRow.Company_Name}}\n",
  "textAlign": "LEFT",
  "textColor": "#231F20",
  "topRow": 0,
  "type": "TEXT_WIDGET",
  "version": 1,
  "widgetId": "knrjogts8y",
  "widgetName": "Text6"
}